MANIFEST.in
Makefile
bootstrap.py
buildout.cfg
changes.txt
plone-3.1.cfg
plone-3.2.cfg
plone-3.3.cfg
plone-base.cfg
plone.cfg
setup.py
version.txt
docs/Makefile
docs/conf.py
docs/index.txt
docs/_build/doctrees/environment.pickle
docs/_build/doctrees/index.doctree
docs/_build/html/.buildinfo
docs/_build/html/genindex.html
docs/_build/html/index.html
docs/_build/html/objects.inv
docs/_build/html/search.html
docs/_build/html/searchindex.js
docs/_build/html/_sources/index.txt
docs/_build/html/_static/adctheme.css
docs/_build/html/_static/basic.css
docs/_build/html/_static/breadcrumb_background.png
docs/_build/html/_static/doctools.js
docs/_build/html/_static/documentation.png
docs/_build/html/_static/file.png
docs/_build/html/_static/header_sm_mid.png
docs/_build/html/_static/jquery.js
docs/_build/html/_static/minus.png
docs/_build/html/_static/plus.png
docs/_build/html/_static/pygments.css
docs/_build/html/_static/scrn1.png
docs/_build/html/_static/scrn2.png
docs/_build/html/_static/searchfield_leftcap.png
docs/_build/html/_static/searchfield_repeat.png
docs/_build/html/_static/searchfield_rightcap.png
docs/_build/html/_static/searchtools.js
docs/_build/html/_static/title_background.png
docs/_build/html/_static/toc.js
docs/_build/html/_static/triangle_closed.png
docs/_build/html/_static/triangle_left.png
docs/_build/html/_static/triangle_open.png
docs/_theme/ADCTheme/LICENSE
docs/_theme/ADCTheme/README.rst
docs/_theme/ADCTheme/layout.html
docs/_theme/ADCTheme/theme.conf
docs/_theme/ADCTheme/static/adctheme.css
docs/_theme/ADCTheme/static/breadcrumb_background.png
docs/_theme/ADCTheme/static/documentation.png
docs/_theme/ADCTheme/static/header_sm_mid.png
docs/_theme/ADCTheme/static/scrn1.png
docs/_theme/ADCTheme/static/scrn2.png
docs/_theme/ADCTheme/static/searchfield_leftcap.png
docs/_theme/ADCTheme/static/searchfield_repeat.png
docs/_theme/ADCTheme/static/searchfield_rightcap.png
docs/_theme/ADCTheme/static/title_background.png
docs/_theme/ADCTheme/static/toc.js
ore.contentmirror.egg-info/PKG-INFO
ore.contentmirror.egg-info/SOURCES.txt
ore.contentmirror.egg-info/dependency_links.txt
ore.contentmirror.egg-info/entry_points.txt
ore.contentmirror.egg-info/namespace_packages.txt
ore.contentmirror.egg-info/not-zip-safe
ore.contentmirror.egg-info/requires.txt
ore.contentmirror.egg-info/top_level.txt
ore/ore.contentmirror.egg-info/SOURCES.txt
ore/ore.contentmirror.egg-info/dependency_links.txt
ore/ore.contentmirror.egg-info/entry_points.txt
ore/ore.contentmirror.egg-info/namespace_packages.txt
ore/ore.contentmirror.egg-info/requires.txt
ore/ore.contentmirror.egg-info/top_level.txt