Metadata-Version: 1.0
Name: ore.contentmirror
Version: 0.7.1
Summary: Deploy Content from Plone to a Relational Database
Home-page: http://contentmirror.googlecode.com
Author: Kapil Thangavelu
Author-email: kapil.foss@gmail.com
License: GPL
Keywords: plone zope zope3
Platform: UNKNOWN
